lute_mandarin_parser/__init__.py
lute_mandarin_parser/parser.py
lute3_mandarin-0.0.3.dist-info/entry_points.txt
lute3_mandarin-0.0.3.dist-info/WHEEL
lute3_mandarin-0.0.3.dist-info/METADATA
lute3_mandarin-0.0.3.dist-info/RECORD
